HelloWord.py
pip_install_name-0.0.2.dist-info/METADATA
pip_install_name-0.0.2.dist-info/WHEEL
pip_install_name-0.0.2.dist-info/top_level.txt
pip_install_name-0.0.2.dist-info/RECORD
